cnert/__init__.py
cnert/py.typed
cnert-0.8.4.dist-info/LICENSE
cnert-0.8.4.dist-info/LICENSE.apache2
cnert-0.8.4.dist-info/LICENSE.mit
cnert-0.8.4.dist-info/METADATA
cnert-0.8.4.dist-info/WHEEL
cnert-0.8.4.dist-info/RECORD
