Metadata-Version: 2.1
Name: cnert
Version: 0.8.4
Summary: Cnert is trying to be a simple API for creating TLS Certificates testing purposes.
Home-page: https://github.com/maartenq/cnert
License: MIT
Keywords: certificate,X.509,TLS,cryptography,testing
Author: Maarten
Author-email: ikmaarten@gmail.com
Requires-Python: >=3.9,<4.0
Classifier: Development Status :: 4 - Beta
Classifier: Environment :: Console
Classifier: Intended Audience :: Developers
Classifier: Intended Audience :: System Administrators
Classifier: License :: OSI Approved :: Apache Software License
Classifier: License :: OSI Approved :: MIT License
Classifier: Natural Language :: English
Classifier: Operating System :: OS Independent
Classifier: Programming Language :: Python
Classifier: Programming Language :: Python :: 3
Classifier: Programming Language :: Python :: 3.9
Classifier: Programming Language :: Python :: 3.10
Classifier: Programming Language :: Python :: 3.11
Classifier: Programming Language :: Python :: 3.12
Classifier: Programming Language :: Python :: 3 :: Only
Classifier: Programming Language :: Python :: Implementation :: CPython
Classifier: Topic :: Security :: Cryptography
Classifier: Topic :: Software Development :: Libraries :: Python Modules
Classifier: Topic :: Software Development :: Testing
Classifier: Topic :: Software Development :: Testing :: Mocking
Requires-Dist: cryptography (>=43.0,<43.1)
Requires-Dist: idna (>=3.8,<3.9)
Project-URL: Documentation, https://cnert.readthedocs.io/en/latest/
Project-URL: Repository, https://github.com/maartenq/cnert
